pykevoplus/__init__.py
pykevoplusnew-3.0.0.dist-info/LICENSE
pykevoplusnew-3.0.0.dist-info/METADATA
pykevoplusnew-3.0.0.dist-info/WHEEL
pykevoplusnew-3.0.0.dist-info/top_level.txt
pykevoplusnew-3.0.0.dist-info/RECORD
