Metadata-Version: 2.1
Name: pykevoplusnew
Version: 3.0.0
Summary: Control Kwikset Kevo locks
Home-page: https://github.com/dcmeglio/pykevoplus
Author: Dominick Meglio
Author-email: dmeglio@gmail.com
License: MIT
Keywords: kevo kwikset
License-File: LICENSE
Requires-Dist: requests
Requires-Dist: beautifulsoup4
